aio/api/bazel/__init__.py
aio/api/bazel/bazel.py
aio/api/bazel/exceptions.py
aio/api/bazel/interface.py
aio/api/bazel/py.typed
aio/api/bazel/worker.py
aio/api/bazel/worker_cmd.py
aio/api/bazel/abstract/__init__.py
aio/api/bazel/abstract/base.py
aio/api/bazel/abstract/env.py
aio/api/bazel/abstract/query.py
aio/api/bazel/abstract/run.py
aio/api/bazel/abstract/worker.py
aio_api_bazel-0.0.4.dist-info/METADATA
aio_api_bazel-0.0.4.dist-info/WHEEL
aio_api_bazel-0.0.4.dist-info/entry_points.txt
aio_api_bazel-0.0.4.dist-info/namespace_packages.txt
aio_api_bazel-0.0.4.dist-info/top_level.txt
aio_api_bazel-0.0.4.dist-info/RECORD
