Metadata-Version: 2.1
Name: aio-api-bazel
Version: 0.0.4
Summary: Async wrapper around bazel
Home-page: https://bazel.com/envoyproxy/toolshed/tree/main/aio.api.bazel
Author: Ryan Northey
Author-email: ryan@synca.io
Maintainer: Ryan Northey
Maintainer-email: ryan@synca.io
License: Apache Software License 2.0
Requires-Python: >=3.11.0
Requires-Dist: abstracts (>=0.0.12)
Requires-Dist: aio.core (>=0.10.5)
Requires-Dist: aio.run.runner (>=0.3.4)
